auradata/__init__.py
auradata/auradata.py
auradata-1.0.2.dist-info/LICENSE
auradata-1.0.2.dist-info/METADATA
auradata-1.0.2.dist-info/WHEEL
auradata-1.0.2.dist-info/top_level.txt
auradata-1.0.2.dist-info/RECORD
