Metadata-Version: 2.2
Name: auradata
Version: 1.0.2
Summary: AuraData: A data-centric auditing and diagnostics engine for machine learning datasets, designed to detect noise, duplicates, label issues, and subgroup risks with transparent reporting.
Home-page: https://github.com/Luckyy0311
Author: Abdul Mofique Siddiqui
Author-email: mofique7860@gmail.com
License: MIT
Classifier: Development Status :: 4 - Beta
Classifier: Intended Audience :: Science/Research
Classifier: Intended Audience :: Developers
Classifier: License :: OSI Approved :: MIT License
Classifier: Programming Language :: Python :: 3
Classifier: Topic :: Scientific/Engineering :: Artificial Intelligence
Classifier: Topic :: Software Development :: Quality Assurance
Requires-Python: >=3.8
License-File: LICENSE
Requires-Dist: numpy>=1.20
Requires-Dist: pandas>=1.0
Requires-Dist: scikit-learn>=1.0
Dynamic: author
Dynamic: author-email
Dynamic: classifier
Dynamic: description
Dynamic: description-content-type
Dynamic: home-page
Dynamic: license
Dynamic: requires-dist
Dynamic: requires-python
Dynamic: summary
